{
    "name": "step06_ori.png",
    "resolution": {
        "width": 2560,
        "height": 1440
    },
    "task_info": {
        "task_description": "9我要在 VS Code 的当前项目中，为页面按钮添加 click 事件监听，实现点击后弹出 “操作成功” 提示框的功能",
        "step_description": "文本输入'<button id=\"myButton\">点击我</button>'，位于屏幕中央偏上,代码编辑器面板中<body>标签内,代码区域第11行,用于添加一个按钮元素。",
        "element": {
            "element_position": {
                "x1": 630,
                "y1": 395,
                "x2": 2425,
                "y2": 422
            }
        },
        "status": "Continue",
        "tag": "Normal",
        "action": "TYPE",
        "value": "<button id=\"myButton\">点击我</button>",
        "step_id": 6,
        "task_id": "0009"
    }
}